rm_pySAS/__init__.py
rm_pysas-0.0.1.dist-info/METADATA
rm_pysas-0.0.1.dist-info/WHEEL
rm_pysas-0.0.1.dist-info/licenses/LICENSE
rm_pysas-0.0.1.dist-info/RECORD
