Metadata-Version: 2.1
Name: rm_pySAS
Version: 0.0.1
Summary: Python library for easy development of apps for reMarkable tablet in Python.
Project-URL: Homepage, https://github.com/tenJirka/rm-pySAS
Author-email: tenJirka <jirka.steh@gmail.com>
License-File: LICENSE
Classifier: License :: OSI Approved :: MIT License
Classifier: Operating System :: OS Independent
Classifier: Programming Language :: Python :: 3
Requires-Python: >=3.7
